myopic_mces/MCES_ILP.py
myopic_mces/__init__.py
myopic_mces/filter_MCES.py
myopic_mces/filter_dataset.py
myopic_mces/graph.py
myopic_mces/myopic_mces.py
myopic_mces/prepare_input.py
myopic_mces-1.0.1.dist-info/METADATA
myopic_mces-1.0.1.dist-info/WHEEL
myopic_mces-1.0.1.dist-info/entry_points.txt
myopic_mces-1.0.1.dist-info/licenses/LICENSE
myopic_mces-1.0.1.dist-info/RECORD
