Metadata-Version: 2.3
Name: myopic_mces
Version: 1.0.1
Summary: A package for computation of the myopic MCES distance
Project-URL: Homepage, https://github.com/AlBi-HHU/myopic-mces
Project-URL: Bug Tracker, https://github.com/AlBi-HHU/myopic-mces/issues
Project-URL: Publication, https://doi.org/10.1101/2023.03.27.534311
License: MIT License
License-File: LICENSE
Classifier: License :: OSI Approved :: MIT License
Classifier: Operating System :: OS Independent
Classifier: Programming Language :: Python :: 3
Requires-Python: >=3.6
Requires-Dist: joblib>=1.2.0
Requires-Dist: networkx>=3.0
Requires-Dist: pulp>=2.7.0
Requires-Dist: rdkit>=2022.09.5
Requires-Dist: scipy>=1.10.1
